search_engines_kit/__init__.py
search_engines_kit/config.py
search_engines_kit/engine.py
search_engines_kit/http_client.py
search_engines_kit/multiple_search_engines.py
search_engines_kit/output.py
search_engines_kit/results.py
search_engines_kit/utils.py
search_engines_kit/engines/__init__.py
search_engines_kit/engines/aol.py
search_engines_kit/engines/ask.py
search_engines_kit/engines/bing.py
search_engines_kit/engines/brave.py
search_engines_kit/engines/dogpile.py
search_engines_kit/engines/duckduckgo.py
search_engines_kit/engines/google.py
search_engines_kit/engines/metager.py
search_engines_kit/engines/mojeek.py
search_engines_kit/engines/qwant.py
search_engines_kit/engines/startpage.py
search_engines_kit/engines/torch.py
search_engines_kit/engines/yahoo.py
search_engines_kit/libs/__init__.py
search_engines_kit/libs/get_terminal_size.py
search_engines_kit/libs/windows_cmd_encoding.py
search_engines_kit/search_results/__init__.py
search_engines_kit-1.0.dist-info/LICENSE
search_engines_kit-1.0.dist-info/METADATA
search_engines_kit-1.0.dist-info/WHEEL
search_engines_kit-1.0.dist-info/top_level.txt
search_engines_kit-1.0.dist-info/RECORD
