Metadata-Version: 2.1
Name: search-engines-kit
Version: 1.0
Summary: Search Engines Scraper
Home-page: https://github.com/Juanchobanano/Search-Engines-Scraper
Keywords: search,browsers
License-File: LICENSE
Requires-Dist: requests[socks] >=2.22.0
Requires-Dist: beautifulsoup4 >=4.10.0
